meshwell/__init__.py
meshwell/cad.py
meshwell/config.py
meshwell/geometry_entity.py
meshwell/gmsh_entity.py
meshwell/import_gds.py
meshwell/labeledentity.py
meshwell/mesh.py
meshwell/model.py
meshwell/polyline.py
meshwell/polyprism.py
meshwell/polysurface.py
meshwell/quality.py
meshwell/remesh.py
meshwell/resolution.py
meshwell/tag.py
meshwell/utils.py
meshwell/validation.py
meshwell/visualization.py
meshwell-2.2.0.dist-info/licenses/LICENSE
meshwell-2.2.0.dist-info/WHEEL
meshwell-2.2.0.dist-info/METADATA
meshwell-2.2.0.dist-info/RECORD
